<?xml version="1.0" encoding="UTF-8"?>
<databaseChangeLog
        xmlns="http://www.liquibase.org/xml/ns/dbchangelog"
        xmlns:xsi="http://www.w3.org/2001/XMLSchema-instance"
        xsi:schemaLocation="http://www.liquibase.org/xml/ns/dbchangelog
        https://www.liquibase.org/xml/ns/dbchangelog/dbchangelog-4.4.xsd">

    <changeSet id="marketplace-seed-fix-v2" author="Ibrogimov Zafar">

        <!-- Расширяем колонку size для поддержки длинных строк (Двойная, Маленький и т.д.) -->
        <modifyDataType tableName="product_variants" columnName="size" newDataType="varchar(20)"/>

        <!-- Очищаем все данные продуктов для чистого старта -->
        <sql>SET FOREIGN_KEY_CHECKS=0</sql>
        <delete tableName="cart_items"/>
        <delete tableName="favorite_products"/>
        <delete tableName="product_variants"/>
        <delete tableName="products"/>
        <delete tableName="sellers"/>
        <sql>DELETE FROM users WHERE email IN ('urbanbrew@mail.ru','boulangerie@mail.ru','freshbites@mail.ru','spiceroute@mail.ru','greenbowl@mail.ru')</sql>
        <sql>SET FOREIGN_KEY_CHECKS=1</sql>

        <!-- Обновляем категории -->
        <sql>UPDATE product_categories SET type='Кофе'     WHERE id=1</sql>
        <sql>UPDATE product_categories SET type='Напитки'  WHERE id=2</sql>
        <sql>UPDATE product_categories SET type='Выпечка'  WHERE id=3</sql>
        <sql>INSERT INTO product_categories (type) SELECT 'Сандвичи' WHERE NOT EXISTS (SELECT 1 FROM product_categories WHERE type='Сандвичи')</sql>
        <sql>INSERT INTO product_categories (type) SELECT 'Десерты'  WHERE NOT EXISTS (SELECT 1 FROM product_categories WHERE type='Десерты')</sql>
        <sql>INSERT INTO product_categories (type) SELECT 'Завтраки' WHERE NOT EXISTS (SELECT 1 FROM product_categories WHERE type='Завтраки')</sql>
        <sql>INSERT INTO product_categories (type) SELECT 'Специи'   WHERE NOT EXISTS (SELECT 1 FROM product_categories WHERE type='Специи')</sql>
        <sql>INSERT INTO product_categories (type) SELECT 'Салаты'   WHERE NOT EXISTS (SELECT 1 FROM product_categories WHERE type='Салаты')</sql>

        <!-- ── Продавцы: создаём пользователей ──────────────────────────────── -->
        <sql>INSERT INTO users (email, name, password_hash, role) VALUES ('urbanbrew@mail.ru',  'Артём Кофейников',  '$2a$10$DQSlDbBO0lWQTsy8Whk0n.SwJo5UMPPRmM/YuNY6wzvEs1ZQNY68C', 'SELLER')</sql>
        <sql>INSERT INTO users (email, name, password_hash, role) VALUES ('boulangerie@mail.ru','Мария Булочкина',   '$2a$10$DQSlDbBO0lWQTsy8Whk0n.SwJo5UMPPRmM/YuNY6wzvEs1ZQNY68C', 'SELLER')</sql>
        <sql>INSERT INTO users (email, name, password_hash, role) VALUES ('freshbites@mail.ru', 'Дмитрий Свежев',   '$2a$10$DQSlDbBO0lWQTsy8Whk0n.SwJo5UMPPRmM/YuNY6wzvEs1ZQNY68C', 'SELLER')</sql>
        <sql>INSERT INTO users (email, name, password_hash, role) VALUES ('spiceroute@mail.ru', 'Алия Пряникова',   '$2a$10$DQSlDbBO0lWQTsy8Whk0n.SwJo5UMPPRmM/YuNY6wzvEs1ZQNY68C', 'SELLER')</sql>
        <sql>INSERT INTO users (email, name, password_hash, role) VALUES ('greenbowl@mail.ru',  'Никита Зеленцов',  '$2a$10$DQSlDbBO0lWQTsy8Whk0n.SwJo5UMPPRmM/YuNY6wzvEs1ZQNY68C', 'SELLER')</sql>

        <!-- ── Продавцы: создаём магазины ──────────────────────────────────── -->
        <sql>INSERT INTO sellers (user_id, name, description, category, rating, is_active) SELECT id, 'Urban Brew', 'Авторский кофе из зёрен со всего мира. Каждая чашка — история о вкусе и качестве.', 'Кофейня', 4.9, true FROM users WHERE email='urbanbrew@mail.ru'</sql>
        <sql>INSERT INTO sellers (user_id, name, description, category, rating, is_active) SELECT id, 'La Boulangerie', 'Свежая французская выпечка и изысканные десерты по рецептам парижских кондитеров.', 'Пекарня', 4.8, true FROM users WHERE email='boulangerie@mail.ru'</sql>
        <sql>INSERT INTO sellers (user_id, name, description, category, rating, is_active) SELECT id, 'Fresh Bites', 'Сытные сэндвичи и завтраки из свежих локальных продуктов. Быстро, вкусно, полезно.', 'Кухня', 4.7, true FROM users WHERE email='freshbites@mail.ru'</sql>
        <sql>INSERT INTO sellers (user_id, name, description, category, rating, is_active) SELECT id, 'Spice Route', 'Восточные специи и блюда с ароматом далёких стран. Откройте мир новых вкусов.', 'Восточная кухня', 4.6, true FROM users WHERE email='spiceroute@mail.ru'</sql>
        <sql>INSERT INTO sellers (user_id, name, description, category, rating, is_active) SELECT id, 'Green Bowl', 'Свежие салаты, боулы и полезная еда для тех, кто заботится о здоровье.', 'Здоровое питание', 4.8, true FROM users WHERE email='greenbowl@mail.ru'</sql>

        <!-- ── Сохраняем ID продавцов в переменные ──────────────────────────── -->
        <sql>SET @urban   = (SELECT id FROM sellers WHERE name='Urban Brew')</sql>
        <sql>SET @boul    = (SELECT id FROM sellers WHERE name='La Boulangerie')</sql>
        <sql>SET @fresh   = (SELECT id FROM sellers WHERE name='Fresh Bites')</sql>
        <sql>SET @spice   = (SELECT id FROM sellers WHERE name='Spice Route')</sql>
        <sql>SET @green   = (SELECT id FROM sellers WHERE name='Green Bowl')</sql>

        <!-- ── Сохраняем ID категорий ──────────────────────────────────────── -->
        <sql>SET @cat_coffee   = (SELECT id FROM product_categories WHERE type='Кофе')</sql>
        <sql>SET @cat_drinks   = (SELECT id FROM product_categories WHERE type='Напитки')</sql>
        <sql>SET @cat_bakery   = (SELECT id FROM product_categories WHERE type='Выпечка')</sql>
        <sql>SET @cat_sandwich = (SELECT id FROM product_categories WHERE type='Сандвичи')</sql>
        <sql>SET @cat_dessert  = (SELECT id FROM product_categories WHERE type='Десерты')</sql>
        <sql>SET @cat_breakfast= (SELECT id FROM product_categories WHERE type='Завтраки')</sql>
        <sql>SET @cat_spice    = (SELECT id FROM product_categories WHERE type='Специи')</sql>
        <sql>SET @cat_salad    = (SELECT id FROM product_categories WHERE type='Салаты')</sql>

        <!-- ═══════════════════════════════════════════════════════════════════ -->
        <!-- ── Urban Brew: горячий кофе (12 товаров) ──────────────────────── -->
        <!-- ═══════════════════════════════════════════════════════════════════ -->
        <sql>INSERT INTO products (type_id, name, description, image_name, seller_id) VALUES (@cat_coffee, 'Эспрессо',    'Классический итальянский эспрессо из отборных зёрен с насыщенным ароматом и плотной крема.',      'espresso.jpg',    @urban)</sql>
        <sql>INSERT INTO products (type_id, name, description, image_name, seller_id) VALUES (@cat_coffee, 'Американо',   'Эспрессо с горячей водой — мягкий ароматный напиток для бодрого старта дня.',                    'americano.jpg',   @urban)</sql>
        <sql>INSERT INTO products (type_id, name, description, image_name, seller_id) VALUES (@cat_coffee, 'Капучино',    'Нежный эспрессо с пышной молочной пеной — идеальный баланс вкуса и аромата.',                    'cappuccino.jpg',  @urban)</sql>
        <sql>INSERT INTO products (type_id, name, description, image_name, seller_id) VALUES (@cat_coffee, 'Латте',       'Мягкий кофе с большим количеством взбитого молока и тонким слоем пены.',                         'latte.jpg',       @urban)</sql>
        <sql>INSERT INTO products (type_id, name, description, image_name, seller_id) VALUES (@cat_coffee, 'Мокко',       'Эспрессо с шоколадным сиропом и взбитым молоком — сладкое кофейное удовольствие.',                'mocha.jpg',       @urban)</sql>
        <sql>INSERT INTO products (type_id, name, description, image_name, seller_id) VALUES (@cat_coffee, 'Макиато',     'Эспрессо с небольшой каплей нежной молочной пены — насыщенный вкус с мягким финишем.',            'macchiato.jpg',   @urban)</sql>
        <sql>INSERT INTO products (type_id, name, description, image_name, seller_id) VALUES (@cat_coffee, 'Лунго',       'Длинный эспрессо с большим количеством воды — мягкий и ароматный напиток.',                       'lungo.jpg',       @urban)</sql>
        <sql>INSERT INTO products (type_id, name, description, image_name, seller_id) VALUES (@cat_coffee, 'Ристретто',   'Короткий концентрированный эспрессо — самый насыщенный кофейный опыт.',                          'ristretto.jpg',   @urban)</sql>
        <sql>INSERT INTO products (type_id, name, description, image_name, seller_id) VALUES (@cat_coffee, 'Флэт Уайт',  'Двойной эспрессо с бархатным микропенным молоком — фаворит кофейной культуры.',                  'flat_white.jpg',  @urban)</sql>
        <sql>INSERT INTO products (type_id, name, description, image_name, seller_id) VALUES (@cat_coffee, 'Аффогато',    'Шарик ванильного мороженого, залитый горячим эспрессо — итальянский десертный кофе.',            'affogato.jpg',    @urban)</sql>
        <sql>INSERT INTO products (type_id, name, description, image_name, seller_id) VALUES (@cat_coffee, 'Корретто',    'Эспрессо с добавлением граппы или ликёра — итальянская классика для особых моментов.',           'corretto.jpg',    @urban)</sql>
        <sql>INSERT INTO products (type_id, name, description, image_name, seller_id) VALUES (@cat_coffee, 'Доппио',      'Двойная порция эспрессо для настоящих ценителей крепкого кофе.',                                 'doppio.jpg',      @urban)</sql>

        <!-- ── Urban Brew: холодные напитки (6 товаров) ────────────────────── -->
        <sql>INSERT INTO products (type_id, name, description, image_name, seller_id) VALUES (@cat_drinks, 'Колд Брю',       'Кофе холодного заваривания — 12 часов настаивания для мягкого вкуса без горечи.',               'cold_brew.jpg',      @urban)</sql>
        <sql>INSERT INTO products (type_id, name, description, image_name, seller_id) VALUES (@cat_drinks, 'Нитро Колд Брю', 'Колд брю под давлением азота — кремовая текстура и мягкий вкус без горечи.',                   'nitro_cold_brew.jpg',@urban)</sql>
        <sql>INSERT INTO products (type_id, name, description, image_name, seller_id) VALUES (@cat_drinks, 'Айс Латте',      'Охлаждённый эспрессо с холодным молоком и льдом. Идеален для жаркого дня.',                    'iced_latte.jpg',     @urban)</sql>
        <sql>INSERT INTO products (type_id, name, description, image_name, seller_id) VALUES (@cat_drinks, 'Айс Американо',  'Охлаждённый американо со льдом — освежающий кофейный напиток в любую погоду.',                 'iced_americano.jpg', @urban)</sql>
        <sql>INSERT INTO products (type_id, name, description, image_name, seller_id) VALUES (@cat_drinks, 'Айс Мокко',      'Холодный шоколадный кофейный напиток со льдом — сладкое летнее удовольствие.',                 'iced_mocha.jpg',     @urban)</sql>
        <sql>INSERT INTO products (type_id, name, description, image_name, seller_id) VALUES (@cat_drinks, 'Фраппе',         'Взбитый холодный кофейный напиток с молоком — освежающий и бодрящий.',                         'frappe.jpg',         @urban)</sql>

        <!-- ── Urban Brew: варианты S/M/L -->
        <sql>SET @p = (SELECT id FROM products WHERE name='Эспрессо'    AND seller_id=@urban)</sql>
        <sql>INSERT INTO product_variants (coffee_id, size, price) VALUES (@p,'S',149.00)</sql>
        <sql>INSERT INTO product_variants (coffee_id, size, price) VALUES (@p,'M',189.00)</sql>
        <sql>INSERT INTO product_variants (coffee_id, size, price) VALUES (@p,'L',229.00)</sql>

        <sql>SET @p = (SELECT id FROM products WHERE name='Американо'   AND seller_id=@urban)</sql>
        <sql>INSERT INTO product_variants (coffee_id, size, price) VALUES (@p,'S',159.00)</sql>
        <sql>INSERT INTO product_variants (coffee_id, size, price) VALUES (@p,'M',199.00)</sql>
        <sql>INSERT INTO product_variants (coffee_id, size, price) VALUES (@p,'L',239.00)</sql>

        <sql>SET @p = (SELECT id FROM products WHERE name='Капучино'    AND seller_id=@urban)</sql>
        <sql>INSERT INTO product_variants (coffee_id, size, price) VALUES (@p,'S',199.00)</sql>
        <sql>INSERT INTO product_variants (coffee_id, size, price) VALUES (@p,'M',249.00)</sql>
        <sql>INSERT INTO product_variants (coffee_id, size, price) VALUES (@p,'L',299.00)</sql>

        <sql>SET @p = (SELECT id FROM products WHERE name='Латте'       AND seller_id=@urban)</sql>
        <sql>INSERT INTO product_variants (coffee_id, size, price) VALUES (@p,'S',219.00)</sql>
        <sql>INSERT INTO product_variants (coffee_id, size, price) VALUES (@p,'M',269.00)</sql>
        <sql>INSERT INTO product_variants (coffee_id, size, price) VALUES (@p,'L',319.00)</sql>

        <sql>SET @p = (SELECT id FROM products WHERE name='Мокко'       AND seller_id=@urban)</sql>
        <sql>INSERT INTO product_variants (coffee_id, size, price) VALUES (@p,'S',229.00)</sql>
        <sql>INSERT INTO product_variants (coffee_id, size, price) VALUES (@p,'M',279.00)</sql>
        <sql>INSERT INTO product_variants (coffee_id, size, price) VALUES (@p,'L',329.00)</sql>

        <sql>SET @p = (SELECT id FROM products WHERE name='Макиато'     AND seller_id=@urban)</sql>
        <sql>INSERT INTO product_variants (coffee_id, size, price) VALUES (@p,'S',179.00)</sql>
        <sql>INSERT INTO product_variants (coffee_id, size, price) VALUES (@p,'M',219.00)</sql>
        <sql>INSERT INTO product_variants (coffee_id, size, price) VALUES (@p,'L',259.00)</sql>

        <sql>SET @p = (SELECT id FROM products WHERE name='Лунго'       AND seller_id=@urban)</sql>
        <sql>INSERT INTO product_variants (coffee_id, size, price) VALUES (@p,'S',169.00)</sql>
        <sql>INSERT INTO product_variants (coffee_id, size, price) VALUES (@p,'M',209.00)</sql>
        <sql>INSERT INTO product_variants (coffee_id, size, price) VALUES (@p,'L',249.00)</sql>

        <sql>SET @p = (SELECT id FROM products WHERE name='Ристретто'   AND seller_id=@urban)</sql>
        <sql>INSERT INTO product_variants (coffee_id, size, price) VALUES (@p,'S',149.00)</sql>
        <sql>INSERT INTO product_variants (coffee_id, size, price) VALUES (@p,'M',189.00)</sql>
        <sql>INSERT INTO product_variants (coffee_id, size, price) VALUES (@p,'L',229.00)</sql>

        <sql>SET @p = (SELECT id FROM products WHERE name='Флэт Уайт'  AND seller_id=@urban)</sql>
        <sql>INSERT INTO product_variants (coffee_id, size, price) VALUES (@p,'S',219.00)</sql>
        <sql>INSERT INTO product_variants (coffee_id, size, price) VALUES (@p,'M',269.00)</sql>
        <sql>INSERT INTO product_variants (coffee_id, size, price) VALUES (@p,'L',319.00)</sql>

        <sql>SET @p = (SELECT id FROM products WHERE name='Аффогато'    AND seller_id=@urban)</sql>
        <sql>INSERT INTO product_variants (coffee_id, size, price) VALUES (@p,'S',259.00)</sql>
        <sql>INSERT INTO product_variants (coffee_id, size, price) VALUES (@p,'M',309.00)</sql>
        <sql>INSERT INTO product_variants (coffee_id, size, price) VALUES (@p,'L',359.00)</sql>

        <sql>SET @p = (SELECT id FROM products WHERE name='Корретто'    AND seller_id=@urban)</sql>
        <sql>INSERT INTO product_variants (coffee_id, size, price) VALUES (@p,'S',239.00)</sql>
        <sql>INSERT INTO product_variants (coffee_id, size, price) VALUES (@p,'M',289.00)</sql>
        <sql>INSERT INTO product_variants (coffee_id, size, price) VALUES (@p,'L',339.00)</sql>

        <sql>SET @p = (SELECT id FROM products WHERE name='Доппио'      AND seller_id=@urban)</sql>
        <sql>INSERT INTO product_variants (coffee_id, size, price) VALUES (@p,'S',169.00)</sql>
        <sql>INSERT INTO product_variants (coffee_id, size, price) VALUES (@p,'M',209.00)</sql>
        <sql>INSERT INTO product_variants (coffee_id, size, price) VALUES (@p,'L',249.00)</sql>

        <sql>SET @p = (SELECT id FROM products WHERE name='Колд Брю'       AND seller_id=@urban)</sql>
        <sql>INSERT INTO product_variants (coffee_id, size, price) VALUES (@p,'S',249.00)</sql>
        <sql>INSERT INTO product_variants (coffee_id, size, price) VALUES (@p,'M',299.00)</sql>
        <sql>INSERT INTO product_variants (coffee_id, size, price) VALUES (@p,'L',349.00)</sql>

        <sql>SET @p = (SELECT id FROM products WHERE name='Нитро Колд Брю' AND seller_id=@urban)</sql>
        <sql>INSERT INTO product_variants (coffee_id, size, price) VALUES (@p,'S',279.00)</sql>
        <sql>INSERT INTO product_variants (coffee_id, size, price) VALUES (@p,'M',329.00)</sql>
        <sql>INSERT INTO product_variants (coffee_id, size, price) VALUES (@p,'L',379.00)</sql>

        <sql>SET @p = (SELECT id FROM products WHERE name='Айс Латте'      AND seller_id=@urban)</sql>
        <sql>INSERT INTO product_variants (coffee_id, size, price) VALUES (@p,'S',239.00)</sql>
        <sql>INSERT INTO product_variants (coffee_id, size, price) VALUES (@p,'M',289.00)</sql>
        <sql>INSERT INTO product_variants (coffee_id, size, price) VALUES (@p,'L',339.00)</sql>

        <sql>SET @p = (SELECT id FROM products WHERE name='Айс Американо'  AND seller_id=@urban)</sql>
        <sql>INSERT INTO product_variants (coffee_id, size, price) VALUES (@p,'S',199.00)</sql>
        <sql>INSERT INTO product_variants (coffee_id, size, price) VALUES (@p,'M',249.00)</sql>
        <sql>INSERT INTO product_variants (coffee_id, size, price) VALUES (@p,'L',299.00)</sql>

        <sql>SET @p = (SELECT id FROM products WHERE name='Айс Мокко'      AND seller_id=@urban)</sql>
        <sql>INSERT INTO product_variants (coffee_id, size, price) VALUES (@p,'S',249.00)</sql>
        <sql>INSERT INTO product_variants (coffee_id, size, price) VALUES (@p,'M',299.00)</sql>
        <sql>INSERT INTO product_variants (coffee_id, size, price) VALUES (@p,'L',349.00)</sql>

        <sql>SET @p = (SELECT id FROM products WHERE name='Фраппе'         AND seller_id=@urban)</sql>
        <sql>INSERT INTO product_variants (coffee_id, size, price) VALUES (@p,'S',249.00)</sql>
        <sql>INSERT INTO product_variants (coffee_id, size, price) VALUES (@p,'M',299.00)</sql>
        <sql>INSERT INTO product_variants (coffee_id, size, price) VALUES (@p,'L',349.00)</sql>


    </changeSet>

</databaseChangeLog>
